{
  "$id" : "https://raw.githubusercontent.com/BHoM/dKoP_Toolkit/TestSchema/.JsonSchema/dKoP/DoorFinish.json",
  "title" : "DoorFinish",
  "type" : "object",
  "properties" : {
    "Exterior" : {
      "$ref" : "https://raw.githubusercontent.com/BHoM/dKoP_Toolkit/TestSchema/.JsonSchema/dKoP/OpeningPartFinish.json"
    },
    "Interior" : {
      "$ref" : "https://raw.githubusercontent.com/BHoM/dKoP_Toolkit/TestSchema/.JsonSchema/dKoP/OpeningPartFinish.json"
    },
    "_t" : {
      "description" : "Optional Type discirminator for BHoM type.",
      "type" : "string",
      "const" : "BH.oM.dKoP.DoorFinish"
    },
    "_bhomVersion" : {
      "type" : "string",
      "description" : "Optional Version of BHoM used when generating the object."
    }
  },
  "required" : ["Exterior", "Interior"],
  "additionalProperties" : false
}